genesia_templates/__init__.py
genesia_templates/templates/django/README.md
genesia_templates/templates/django/app/__init__.py.jinja
genesia_templates/templates/django/app/admin.py.jinja
genesia_templates/templates/django/app/apps.py.jinja
genesia_templates/templates/django/app/models.py.jinja
genesia_templates/templates/django/app/tests.py.jinja
genesia_templates/templates/django/app/views.py.jinja
genesia_templates/templates/django/manage.py
genesia_templates/templates/django/{{project_name}}/__init__.py
genesia_templates/templates/django/{{project_name}}/asgi.py
genesia_templates/templates/django/{{project_name}}/settings.py
genesia_templates/templates/django/{{project_name}}/urls.py
genesia_templates/templates/django/{{project_name}}/wsgi.py
genesia_templates/templates.py
genesia_templates-0.1.7.dist-info/METADATA
genesia_templates-0.1.7.dist-info/WHEEL
genesia_templates-0.1.7.dist-info/RECORD
