Metadata-Version: 2.1
Name: genesia-templates
Version: 0.1.7
Summary: genesia templates
License: MIT
Author: lucasmrdt
Author-email: lucas.marandat@gmail.com
Requires-Python: >=3.11,<4.0
Classifier: License :: OSI Approved :: MIT License
Classifier: Programming Language :: Python :: 3
Classifier: Programming Language :: Python :: 3.11
Requires-Dist: jinja2 (>=3.1.2,<4.0.0)
